rframe/__init__.py
rframe/_hypothesis_plugin.py
rframe/data_accessor.py
rframe/dispatchers.py
rframe/indexes/__init__.py
rframe/indexes/base.py
rframe/indexes/index.py
rframe/indexes/interpolating_index.py
rframe/indexes/interval_index.py
rframe/indexes/multi_index.py
rframe/interfaces/__init__.py
rframe/interfaces/base.py
rframe/interfaces/json.py
rframe/interfaces/mongo.py
rframe/interfaces/pandas.py
rframe/interfaces/rest.py
rframe/interfaces/tinydb.py
rframe/rest_client.py
rframe/rest_server.py
rframe/rframe.py
rframe/schema.py
rframe/types.py
rframe/utils.py
rframe-0.2.24.dist-info/AUTHORS.rst
rframe-0.2.24.dist-info/LICENSE
rframe-0.2.24.dist-info/METADATA
rframe-0.2.24.dist-info/WHEEL
rframe-0.2.24.dist-info/entry_points.txt
rframe-0.2.24.dist-info/RECORD
