Metadata-Version: 2.3
Name: rframe
Version: 0.2.24
Summary: Top-level package for rframe.
License: MIT
Author: Yossi Mosbacher
Author-email: joe.mosbacher@gmail.com
Requires-Python: >=3.9,<3.13
Classifier: Development Status :: 2 - Pre-Alpha
Classifier: Intended Audience :: Developers
Classifier: License :: OSI Approved :: MIT License
Classifier: Natural Language :: English
Classifier: Programming Language :: Python :: 3
Classifier: Programming Language :: Python :: 3.9
Classifier: Programming Language :: Python :: 3.10
Classifier: Programming Language :: Python :: 3.11
Classifier: Programming Language :: Python :: 3.12
Requires-Dist: fsspec (>=2025.2.0,<2026.0.0)
Requires-Dist: jsonschema (>=4.23.0,<5.0.0)
Requires-Dist: loguru (>=0.7.3,<0.8.0)
Requires-Dist: makefun (>=1.15.6,<2.0.0)
Requires-Dist: pandas
Requires-Dist: plum-dispatch (==2.5.7)
Requires-Dist: pydantic (<2.0)
Requires-Dist: requests (>=2.31.0,<3.0.0)
Requires-Dist: toolz (>=1.0.0,<2.0.0)
Requires-Dist: yapf (==0.43.0)
Project-URL: Homepage, https://github.com/jmosbacher/rframe
